statlab/__all__.py
statlab/__init__.py
statlab/aled.py
statlab/all.py
statlab/ord.py
statlab-0.0.4.dist-info/METADATA
statlab-0.0.4.dist-info/WHEEL
statlab-0.0.4.dist-info/licenses/LICENSE
statlab-0.0.4.dist-info/RECORD
