Metadata-Version: 2.4
Name: statlab
Version: 0.0.4
Summary: A python package offering a variety of statistical and machine learning tools.
Project-URL: Homepage, https://github.com/noamrotenberg/statlab
Author-email: Noam Rotenberg <nrotenb1@alumni.jh.edu>, Zan Chaudhry <zchaudh3@alumni.jh.edu>
License-File: LICENSE
Classifier: Operating System :: OS Independent
Classifier: Programming Language :: Python :: 3
Requires-Python: >=3.8
